kathairo/__init__.py
kathairo/alignments/alignment.py
kathairo/alignments/alignmentSet.py
kathairo/alignments/figuringOutSymmetrizedAlignment.txt
kathairo/alignments/symmetrizedAlignment.py
kathairo/experiments/CUVMPS/create_usfm.py
kathairo/experiments/CUVMPS/create_verse_text.py
kathairo/experiments/CUVMPS/select.py
kathairo/experiments/demonstration.py
kathairo/experiments/usfmValidator.py
kathairo/helpers/paths.py
kathairo/helpers/strings.py
kathairo/helpers/verse_text.py
kathairo/helpers/versification.py
kathairo/parsing/usfm/README.md
kathairo/parsing/usfm/usfm_file_text.py
kathairo/parsing/usfm/usfm_file_text_corpus.py
kathairo/parsing/usfm/usfm_handlers.py
kathairo/parsing/usfm/usfm_text_base.py
kathairo/parsing/usx/README.md
kathairo/parsing/usx/usx_file_text.py
kathairo/parsing/usx/usx_file_text_corpus.py
kathairo/parsing/usx/usx_text_base.py
kathairo/parsing/usx/usx_verse_parser.py
kathairo/tokenization/ChineseBibleWordTokenizer.py
kathairo/tokenization/Data/ChineseBibleWordTokenizer/combination_corrections.txt
kathairo/tokenization/Data/ChineseBibleWordTokenizer/license.txt
kathairo/tokenization/Data/ChineseBibleWordTokenizer/words.txt
kathairo/tokenization/latin_whitespace_included_tokenizer.py
kathairo/tokenization/MaximalMatchingTokenizer.py
kathairo/tokenization/README.md
kathairo/tokenization/regex_rules.py
kathairo/tokenization/whitespace_included_tokenizer.py
kathairo/tsvs/build_tsv.py
kathairo/tsvs/build_tsv_json_parser.py
kathairo/versification/eng.vrs
kathairo/versification/fix_versification.py
kathairo-0.4.5.dist-info/entry_points.txt
kathairo-0.4.5.dist-info/METADATA
kathairo-0.4.5.dist-info/WHEEL
kathairo-0.4.5.dist-info/RECORD
