Metadata-Version: 2.3
Name: kathairo
Version: 0.4.5
Summary: Scripture processing pipeline for converting USFM and USX formats into structured TSV files
Keywords: bible,scripture,usfm,usx,nlp,tokenization,versification
Author: Robertson Brinker
Author-email: robertsonbrinker@gmail.com
Requires-Python: >=3.10,<3.13
Classifier: Development Status :: 4 - Beta
Classifier: Intended Audience :: Developers
Classifier: Intended Audience :: Religion
Classifier: Programming Language :: Python :: 3
Classifier: Programming Language :: Python :: 3.10
Classifier: Programming Language :: Python :: 3.11
Classifier: Programming Language :: Python :: 3.12
Classifier: Topic :: Religion
Classifier: Topic :: Text Processing :: Linguistic
Requires-Dist: polars (>=1.4.0,<2.0.0)
Requires-Dist: sil-machine (==1.8.4)
Requires-Dist: spacy (>=3.7.5,<4.0.0)
Project-URL: Homepage, https://github.com/ClearBible/kathairo.py
Project-URL: Repository, https://github.com/ClearBible/kathairo.py
